cjwt/__init__.py
cjwt/__main__.py
cjwt-0.2.0.dist-info/entry_points.txt
cjwt-0.2.0.dist-info/WHEEL
cjwt-0.2.0.dist-info/METADATA
cjwt-0.2.0.dist-info/RECORD
