Metadata-Version: 2.1
Name: cjwt
Version: 0.2.0
Summary: Simple JWT reader utility
License: MIT
Author: Max Harley
Author-email: maxh@maxh.io
Requires-Python: >=3.10,<4.0
Classifier: License :: OSI Approved :: MIT License
Classifier: Programming Language :: Python :: 3
Classifier: Programming Language :: Python :: 3.10
Requires-Dist: pyjwt (>=2.6.0,<3.0.0)
